CodeSync/__init__.py
CodeSync/codeSyncNet.py
CodeSync/model.py
codeSyncNet-1.1.dist-info/METADATA
codeSyncNet-1.1.dist-info/WHEEL
codeSyncNet-1.1.dist-info/top_level.txt
codeSyncNet-1.1.dist-info/RECORD
