Metadata-Version: 2.1
Name: codeSyncNet
Version: 1.1
Summary: A package to detect the inconsistent between code and text
Author-email: Anh Dau Thi Van <vananh09052000@gmail.com>
Project-URL: Homepage, https://github.com/Fsoft-AIC/CodeSync
Project-URL: Bug Tracker, https://github.com/Fsoft-AIC/CodeSync/issues
Classifier: Programming Language :: Python :: 3
Classifier: License :: OSI Approved :: MIT License
Classifier: Operating System :: OS Independent
Requires-Python: >=3.7
Requires-Dist: gdown (==4.7.1)
Requires-Dist: torch (==1.10.1)
Requires-Dist: transformers (==4.18.0)
